duper/__init__.py
duper/_duper.cpython-313-aarch64-linux-gnu.so
duper/_duper.pyi
duper/fastapi.py
duper/py.typed
duper/pydantic.py
duper_python-0.4.2.dist-info/METADATA
duper_python-0.4.2.dist-info/WHEEL
duper_python-0.4.2.dist-info/licenses/LICENSE
duper_python-0.4.2.dist-info/RECORD
