Metadata-Version: 2.4
Name: duper-python
Version: 0.4.2
Classifier: Programming Language :: Rust
Classifier: Programming Language :: Python :: Implementation :: CPython
Classifier: Programming Language :: Python :: Implementation :: PyPy
Classifier: Topic :: File Formats
Classifier: Framework :: FastAPI
Classifier: Framework :: Pydantic
Classifier: Framework :: Pydantic :: 2
Requires-Dist: pydantic>=2,<3
License-File: LICENSE
Summary: The format that's super!
Keywords: duper,parser,serialization,pydantic,fastapi
Home-Page: https://duper.dev.br
Author-email: Eric Rodrigues Pires <eric@eric.dev.br>
License-Expression: MIT
Requires-Python: >=3.10
Project-URL: homepage, https://duper.dev.br
Project-URL: source, https://github.com/EpicEric/duper
Project-URL: changelog, https://github.com/EpicEric/duper/blob/main/duper-python/CHANGELOG.md
